{
  "main": {
    "id": "2a327d01976d7041",
    "type": "split",
    "children": [
      {
        "id": "9bffd1b8711cb9a7",
        "type": "tabs",
        "children": [
          {
            "id": "f1a5ae53903c2eca",
            "type": "leaf",
            "state": {
              "type": "markdown",
              "state": {
                "file": "thoughts/数字世界的构建手册.md",
                "mode": "source",
                "source": false
              },
              "icon": "lucide-file",
              "title": "数字世界的构建手册"
            }
          },
          {
            "id": "f7b6fd7a4478f70f",
            "type": "leaf",
            "state": {
              "type": "image",
              "state": {
                "file": "public/images/文章资源/数字世界的构建手册/file-20250612000822808.jpg"
              },
              "icon": "lucide-image",
              "title": "file-20250612000822808"
            }
          },
          {
            "id": "1aaab99e7f6448f4",
            "type": "leaf",
            "state": {
              "type": "image",
              "state": {
                "file": "public/images/文章资源/数字世界的构建手册/file-20250612000816606.jpg"
              },
              "icon": "lucide-image",
              "title": "file-20250612000816606"
            }
          },
          {
            "id": "3894c7bc2038414e",
            "type": "leaf",
            "state": {
              "type": "image",
              "state": {
                "file": "public/images/文章资源/数字世界的构建手册/file-20250612000805895.jpg"
              },
              "icon": "lucide-image",
              "title": "file-20250612000805895"
            }
          }
        ]
      }
    ],
    "direction": "vertical"
  },
  "left": {
    "id": "e614729a7ff4aac3",
    "type": "split",
    "children": [
      {
        "id": "d57180d71a95b5ef",
        "type": "tabs",
        "children": [
          {
            "id": "9390bb6f3770f8ef",
            "type": "leaf",
            "state": {
              "type": "outline",
              "state": {
                "file": "thoughts/数字世界的构建手册.md",
                "followCursor": false,
                "showSearch": true,
                "searchQuery": ""
              },
              "icon": "lucide-list",
              "title": "数字世界的构建手册 的大纲"
            }
          },
          {
            "id": "aebed8ba13ee6df8",
            "type": "leaf",
            "state": {
              "type": "bookmarks",
              "state": {},
              "icon": "lucide-bookmark",
              "title": "书签"
            }
          },
          {
            "id": "35b2b112743022f8",
            "type": "leaf",
            "state": {
              "type": "search",
              "state": {
                "query": "",
                "matchingCase": true,
                "explainSearch": false,
                "collapseAll": false,
                "extraContext": false,
                "sortOrder": "alphabetical"
              },
              "icon": "lucide-search",
              "title": "搜索"
            }
          }
        ]
      }
    ],
    "direction": "horizontal",
    "width": 200
  },
  "right": {
    "id": "318f4ed2312b0f42",
    "type": "split",
    "children": [
      {
        "id": "de2db9869ac882b8",
        "type": "tabs",
        "children": [
          {
            "id": "609913dcbebc90fd",
            "type": "leaf",
            "state": {
              "type": "file-explorer",
              "state": {
                "sortOrder": "alphabetical",
                "autoReveal": false
              },
              "icon": "lucide-folder-closed",
              "title": "文件列表"
            }
          },
          {
            "id": "b5c835b74111611c",
            "type": "leaf",
            "state": {
              "type": "backlink",
              "state": {
                "file": "source/_posts/猎识印记-领域/Git-版本控制.md",
                "collapseAll": false,
                "extraContext": false,
                "sortOrder": "alphabetical",
                "showSearch": false,
                "searchQuery": "",
                "backlinkCollapsed": false,
                "unlinkedCollapsed": true
              },
              "icon": "links-coming-in",
              "title": "Git-版本控制 的反向链接列表"
            }
          },
          {
            "id": "f9e1fca7e6683779",
            "type": "leaf",
            "state": {
              "type": "tag",
              "state": {
                "sortOrder": "frequency",
                "useHierarchy": true,
                "showSearch": false,
                "searchQuery": ""
              },
              "icon": "lucide-tags",
              "title": "标签"
            }
          }
        ]
      }
    ],
    "direction": "horizontal",
    "width": 269.5
  },
  "left-ribbon": {
    "hiddenItems": {
      "switcher:打开快速切换": false,
      "graph:查看关系图谱": false,
      "canvas:新建白板": false,
      "templates:插入模板": false,
      "command-palette:打开命令面板": false
    }
  },
  "active": "f1a5ae53903c2eca",
  "lastOpenFiles": [
    "public/images/文章资源/数字世界的构建手册/file-20250612000822808.jpg",
    "thoughts/数字世界的构建手册.md",
    "public/images/文章资源/数字世界的构建手册/file-20250612000816606.jpg",
    "public/images/文章资源/数字世界的构建手册/file-20250612000805895.jpg",
    "public/images/文章资源/数字世界的构建手册/file-20250612000853185.jpg",
    "public/images/文章资源/数字世界的构建手册/file-20250612000843792.jpg",
    "public/images/文章资源/数字世界的构建手册/file-20250612000832734.jpg",
    "public/images/文章资源/数字世界的构建手册",
    "thoughts/环境变量.md",
    "thoughts/远古卷轴.md",
    "thoughts/獠牙下的野蔷薇.md",
    "thoughts/竟然被回关.md",
    "thoughts/光不在彼方.md",
    "thoughts/笔记本 Wi-Fi 消失的解决方法.md",
    "thoughts/从一盏灯开始的文明.md",
    "thoughts/互联网与星辰大海.md",
    "public/images/文章资源/互联网与星辰大海/file-20250611230101428.jpg",
    "public/images/文章资源/互联网与星辰大海/file-20250611230049938.jpg",
    "public/images/文章资源/互联网与星辰大海",
    "knowledge/前端基础/未命名.md",
    "public/images/文章资源/环境变量/file-20250611225312015.jpg",
    "public/images/文章资源/环境变量/file-20250611225305721.jpg",
    "public/images/文章资源/环境变量",
    "thoughts/测试.md",
    "knowledge/前端框架/新增的测试文章.md",
    "public/knowledge-stats.json",
    "projects/online-shoping-vue3.md",
    "_scaffolds/page.md",
    "_scaffolds/post.md",
    "public/images/文章资源/竟然被回关",
    "knowledge/前端框架/Vue Router-路由管理.md",
    "knowledge/前端工具库/Axios-现代化的 Ajax 请求工具.md",
    "knowledge/前端工具库/在项目重封装 Axios 请求.md",
    "thoughts/未命名3.md",
    "thoughts/未命名2.md",
    "thoughts/未命名1.md",
    "thoughts/tags.md",
    "debug-sort.log",
    "knowledge/前端工具库/Element-Plus 定制主题（SCSS 方案）.md",
    "knowledge/前端工具库/ESLint+Prettier 代码规范自动化.md",
    "knowledge/前端工具库/Git-版本控制.md",
    "public/images/文章资源/axios-现代化的-ajax-请求工具",
    "public/images/文章资源/git-版本控制",
    "knowledge/前端工具库",
    "public/images/文章资源/vue2状态管理-vuex",
    "点子合集.canvas"
  ]
}